LICENSE
README.md
setup.cfg
setup.py
singer/__init__.py
singer/bookmarks.py
singer/catalog.py
singer/exceptions.py
singer/logger.py
singer/logging.conf
singer/messages.py
singer/metadata.py
singer/metrics.py
singer/requests.py
singer/schema.py
singer/schema_generation.py
singer/statediff.py
singer/transform.py
singer/utils.py
singer_python.egg-info/PKG-INFO
singer_python.egg-info/SOURCES.txt
singer_python.egg-info/dependency_links.txt
singer_python.egg-info/requires.txt
singer_python.egg-info/top_level.txt
tests/__init__.py
tests/test_bookmarks.py
tests/test_catalog.py
tests/test_exceptions.py
tests/test_metadata.py
tests/test_metrics.py
tests/test_schema.py
tests/test_schema_generation.py
tests/test_singer.py
tests/test_statediff.py
tests/test_transform.py
tests/test_utils.py